cryptobot/__init__.py
cryptobot/_sync/__init__.py
cryptobot/_sync/client.py
cryptobot/_utils.py
cryptobot/errors.py
cryptobot/models/__init__.py
cryptobot/py.typed
cryptobot/webhook.py
cryptobot_python-0.4.1.dist-info/METADATA
cryptobot_python-0.4.1.dist-info/WHEEL
cryptobot_python-0.4.1.dist-info/licenses/AUTHORS.md
cryptobot_python-0.4.1.dist-info/licenses/LICENSE
cryptobot_python-0.4.1.dist-info/RECORD
