Metadata-Version: 2.4
Name: cryptobot-python
Version: 0.4.1
Summary: Non official, but friendly CryptoBot library for the Python language
License: MIT
License-File: AUTHORS.md
License-File: LICENSE
Keywords: cryptocurrency,cryptobot,telegram
Author: Reinier Hernández
Author-email: sasuke.reinier@gmail.com
Requires-Python: >=3.9.12
Classifier: Development Status :: 5 - Production/Stable
Classifier: License :: OSI Approved :: MIT License
Classifier: Programming Language :: Python :: 3.9
Classifier: Programming Language :: Python :: 3.10
Classifier: Programming Language :: Python :: 3.11
Classifier: Programming Language :: Python :: 3.12
Classifier: Programming Language :: Python :: 3.13
Classifier: Programming Language :: Python :: 3.14
Classifier: Topic :: Software Development :: Build Tools
Classifier: Topic :: Software Development :: Libraries :: Python Modules
Provides-Extra: docs
Requires-Dist: colorama (>=0.4.6,<0.5.0)
Requires-Dist: fastapi (>=0.128.0,<0.129.0)
Requires-Dist: httpx (>=0.28.1,<0.29.0)
Requires-Dist: pydantic-core (>=2.41.5,<3.0.0)
Requires-Dist: python-dotenv (>=1.2.1,<2.0.0)
Requires-Dist: tox (>=4.30.3,<5.0.0)
Requires-Dist: twine (>=6.2.0,<7.0.0)
Requires-Dist: uvicorn (>=0.39.0,<0.40.0)
Project-URL: Bug Tracker, https://github.com/ragnarok22/cryptobot_python/issues
Project-URL: Documentation, https://cryptobot-python.readthedocs.io/en/latest
Project-URL: Homepage, https://cryptobot-python.readthedocs.io/en/latest
Project-URL: Repository, https://github.com/ragnarok22/cryptobot_python
